<?xml version="1.0" encoding="ISO-8859-1"?>
<modeling>
 <generator>
  <i name="program" type="string">vasp </i>
  <i name="version" type="string">5.4.4.18Apr17-6-g9f103f2a35  </i>
  <i name="subversion" type="string">(build Apr 28 2018 00:24:27) complex            parallel </i>
  <i name="platform" type="string">LinuxIFC </i>
  <i name="date" type="string">2024 11 29 </i>
  <i name="time" type="string">22:38:03 </i>
 </generator>
 <incar>
  <i type="string" name="SYSTEM"> Relaxation5</i>
  <i type="int" name="ISTART">     0</i>
  <i type="string" name="PREC">normal</i>
  <i type="int" name="IBRION">     2</i>
  <i name="EDIFF">      0.00001000</i>
  <i name="EDIFFG">      0.00010000</i>
  <i type="int" name="NSW">     0</i>
  <i type="int" name="ISIF">     3</i>
  <i name="ENCUT">    600.00000000</i>
  <i name="POTIM">      0.02000000</i>
  <i type="int" name="ISMEAR">     1</i>
  <i name="SIGMA">      0.10000000</i>
  <i name="KSPACING">      0.25000000</i>
  <i name="PSTRESS">      0.00000000</i>
  <i type="logical" name="LWAVE"> F  </i>
  <i type="logical" name="LCHARG"> F  </i>
  <v type="int" name="KPOINT_BSE">    -1     0     0     0</v>
 </incar>
 <structure name="primitive_cell" >
  <crystal>
   <varray name="basis" >
    <v>       6.12463900       0.07338700       0.11643400 </v>
    <v>       0.10284100       6.12337600       0.21606000 </v>
    <v>       0.22619200       0.19802000       5.89217100 </v>
   </varray>
   <i name="volume">    220.51502595 </i>
   <varray name="rec_basis" >
    <v>       0.16342285      -0.00252629      -0.00618867 </v>
    <v>      -0.00185635       0.16353119      -0.00542458 </v>
    <v>      -0.00316130      -0.00594660       0.17003794 </v>
   </varray>
  </crystal>
  <varray name="positions" >
   <v>       0.24546400       0.23212500       0.23084700 </v>
   <v>      -0.06831200       0.32030900       0.44130700 </v>
   <v>       0.34804700       0.47449400      -0.07248300 </v>
   <v>       0.45032700      -0.07763700       0.34010900 </v>
   <v>      -0.03936300      -0.03152300      -0.01809600 </v>
   <v>       0.33859400       0.31511100      -0.29918200 </v>
   <v>      -0.27959900       0.33498400       0.27410200 </v>
   <v>       0.27475100      -0.28202800       0.34199700 </v>
   <v>       0.46317000       0.06007600      -0.28946900 </v>
   <v>      -0.27485100      -0.49721800      -0.01522800 </v>
   <v>       0.00404300      -0.30928600      -0.48357300 </v>
   <v>       0.18090500      -0.18086200      -0.17821100 </v>
   <v>      -0.18966900       0.17152300      -0.19108600 </v>
   <v>      -0.19952900      -0.19993600       0.19867800 </v>
   <v>      -0.23363300      -0.34313500      -0.28470100 </v>
  </varray>
 </structure>
 <varray name="primitive_index" >
  <v type="int" >        1 </v>
  <v type="int" >        8 </v>
  <v type="int" >        5 </v>
  <v type="int" >        7 </v>
  <v type="int" >       11 </v>
  <v type="int" >       14 </v>
  <v type="int" >       12 </v>
  <v type="int" >       13 </v>
  <v type="int" >       10 </v>
  <v type="int" >        6 </v>
  <v type="int" >        9 </v>
  <v type="int" >        4 </v>
  <v type="int" >        3 </v>
  <v type="int" >        2 </v>
  <v type="int" >       15 </v>
 </varray>
 <kpoints>
  <generation param="Gamma">
   <v type="int" name="divisions">       3        3        3 </v>
   <v name="usershift">      0.00000000       0.00000000       0.00000000 </v>
   <v name="genvec1">      0.33333333       0.00000000       0.00000000 </v>
   <v name="genvec2">     -0.00000000       0.33333333       0.00000000 </v>
   <v name="genvec3">      0.00000000      -0.00000000       0.33333333 </v>
   <v name="shift">      0.00000000       0.00000000       0.00000000 </v>
  </generation>
  <varray name="kpointlist" >
   <v>       0.00000000       0.00000000       0.00000000 </v>
   <v>       0.33333333      -0.00000000       0.00000000 </v>
   <v>       0.00000000       0.33333333       0.00000000 </v>
   <v>       0.33333333       0.33333333       0.00000000 </v>
   <v>      -0.33333333       0.33333333      -0.00000000 </v>
   <v>       0.00000000      -0.00000000       0.33333333 </v>
   <v>       0.33333333      -0.00000000       0.33333333 </v>
   <v>      -0.33333333       0.00000000       0.33333333 </v>
   <v>      -0.00000000       0.33333333       0.33333333 </v>
   <v>       0.33333333       0.33333333       0.33333333 </v>
   <v>      -0.33333333       0.33333333       0.33333333 </v>
   <v>      -0.00000000      -0.33333333       0.33333333 </v>
   <v>       0.33333333      -0.33333333       0.33333333 </v>
   <v>      -0.33333333      -0.33333333       0.33333333 </v>
  </varray>
  <varray name="weights" >
   <v>       0.03703704 </v>
   <v>       0.07407407 </v>
   <v>       0.07407407 </v>
   <v>       0.07407407 </v>
   <v>       0.07407407 </v>
   <v>       0.07407407 </v>
   <v>       0.07407407 </v>
   <v>       0.07407407 </v>
   <v>       0.07407407 </v>
   <v>       0.07407407 </v>
   <v>       0.07407407 </v>
   <v>       0.07407407 </v>
   <v>       0.07407407 </v>
   <v>       0.07407407 </v>
  </varray>
 </kpoints>
 <parameters>
  <separator name="general" >
   <i type="string" name="SYSTEM">Relaxation5</i>
   <i type="logical" name="LCOMPAT"> F  </i>
  </separator>
  <separator name="electronic" >
   <i type="string" name="PREC">normal</i>
   <i name="ENMAX">    600.00000000</i>
   <i name="ENAUG">    605.39200000</i>
   <i name="EDIFF">      0.00001000</i>
   <i type="int" name="IALGO">    38</i>
   <i type="int" name="IWAVPR">    10</i>
   <i type="int" name="NBANDS">    48</i>
   <i name="NELECT">     70.00000000</i>
   <i type="int" name="TURBO">     0</i>
   <i type="int" name="IRESTART">     0</i>
   <i type="int" name="NREBOOT">     0</i>
   <i type="int" name="NMIN">     0</i>
   <i name="EREF">      0.00000000</i>
   <separator name="electronic smearing" >
    <i type="int" name="ISMEAR">     1</i>
    <i name="SIGMA">      0.10000000</i>
    <i name="KSPACING">      0.25000000</i>
    <i type="logical" name="KGAMMA"> T  </i>
   </separator>
   <separator name="electronic projectors" >
    <i type="logical" name="LREAL"> F  </i>
    <v name="ROPT">      0.00000000      0.00000000</v>
    <i type="int" name="LMAXPAW">  -100</i>
    <i type="int" name="LMAXMIX">     2</i>
    <i type="logical" name="NLSPLINE"> F  </i>
   </separator>
   <separator name="electronic startup" >
    <i type="int" name="ISTART">     0</i>
    <i type="int" name="ICHARG">     2</i>
    <i type="int" name="INIWAV">     1</i>
   </separator>
   <separator name="electronic spin" >
    <i type="int" name="ISPIN">     1</i>
    <i type="logical" name="LNONCOLLINEAR"> F  </i>
    <v name="MAGMOM">      1.00000000      1.00000000      1.00000000      1.00000000      1.00000000      1.00000000      1.00000000      1.00000000      1.00000000      1.00000000      1.00000000      1.00000000      1.00000000      1.00000000      1.00000000</v>
    <i name="NUPDOWN">     -1.00000000</i>
    <i type="logical" name="LSORBIT"> F  </i>
    <v name="SAXIS">      0.00000000      0.00000000      1.00000000</v>
    <i type="logical" name="LSPIRAL"> F  </i>
    <v name="QSPIRAL">      0.00000000      0.00000000      0.00000000</v>
    <i type="logical" name="LZEROZ"> F  </i>
   </separator>
   <separator name="electronic exchange-correlation" >
    <i type="logical" name="LASPH"> F  </i>
    <i type="logical" name="LMETAGGA"> F  </i>
   </separator>
   <separator name="electronic convergence" >
    <i type="int" name="NELM">    60</i>
    <i type="int" name="NELMDL">    -5</i>
    <i type="int" name="NELMIN">     2</i>
    <i name="ENINI">    600.00000000</i>
    <separator name="electronic convergence detail" >
     <i type="logical" name="LDIAG"> T  </i>
     <i type="logical" name="LSUBROT"> F  </i>
     <i name="WEIMIN">      0.00000000</i>
     <i name="EBREAK">      0.00000005</i>
     <i name="DEPER">      0.30000000</i>
     <i type="int" name="NRMM">     4</i>
     <i name="TIME">      0.40000000</i>
    </separator>
   </separator>
   <separator name="electronic mixer" >
    <i name="AMIX">      0.40000000</i>
    <i name="BMIX">      1.00000000</i>
    <i name="AMIN">      0.10000000</i>
    <i name="AMIX_MAG">      1.60000000</i>
    <i name="BMIX_MAG">      1.00000000</i>
    <separator name="electronic mixer details" >
     <i type="int" name="IMIX">     4</i>
     <i type="logical" name="MIXFIRST"> F  </i>
     <i type="int" name="MAXMIX">   -45</i>
     <i name="WC">    100.00000000</i>
     <i type="int" name="INIMIX">     1</i>
     <i type="int" name="MIXPRE">     1</i>
     <i type="int" name="MREMOVE">     5</i>
    </separator>
   </separator>
   <separator name="electronic dipolcorrection" >
    <i type="logical" name="LDIPOL"> F  </i>
    <i type="logical" name="LMONO"> F  </i>
    <i type="int" name="IDIPOL">     0</i>
    <i name="EPSILON">      1.00000000</i>
    <v name="DIPOL">   -100.00000000   -100.00000000   -100.00000000</v>
    <i name="EFIELD">      0.00000000</i>
   </separator>
  </separator>
  <separator name="grids" >
   <i type="int" name="NGX">    40</i>
   <i type="int" name="NGY">    40</i>
   <i type="int" name="NGZ">    36</i>
   <i type="int" name="NGXF">    80</i>
   <i type="int" name="NGYF">    80</i>
   <i type="int" name="NGZF">    72</i>
   <i type="logical" name="ADDGRID"> F  </i>
  </separator>
  <separator name="ionic" >
   <i type="int" name="NSW">     0</i>
   <i type="int" name="IBRION">    -1</i>
   <i type="int" name="MDALGO">     0</i>
   <i type="int" name="ISIF">     3</i>
   <i name="PSTRESS">      0.00000000</i>
   <i name="EDIFFG">      0.00010000</i>
   <i type="int" name="NFREE">     1</i>
   <i name="POTIM">      0.02000000</i>
   <i name="SMASS">     -3.00000000</i>
   <i name="SCALEE">      1.00000000</i>
  </separator>
  <separator name="ionic md" >
   <i name="TEBEG">      0.00010000</i>
   <i name="TEEND">      0.00010000</i>
   <i type="int" name="NBLOCK">     1</i>
   <i type="int" name="KBLOCK">     1</i>
   <i type="int" name="NPACO">   256</i>
   <i name="APACO">     16.00000000</i>
  </separator>
  <separator name="symmetry" >
   <i type="int" name="ISYM">     2</i>
   <i name="SYMPREC">      0.00001000</i>
  </separator>
  <separator name="dos" >
   <i type="int" name="LORBIT">     0</i>
   <v name="RWIGS">     -1.00000000     -1.00000000</v>
   <i type="int" name="NEDOS">   301</i>
   <i name="EMIN">     10.00000000</i>
   <i name="EMAX">    -10.00000000</i>
   <i name="EFERMI">      0.00000000</i>
  </separator>
  <separator name="writing" >
   <i type="int" name="NWRITE">     2</i>
   <i type="logical" name="LWAVE"> F  </i>
   <i type="logical" name="LDOWNSAMPLE"> F  </i>
   <i type="logical" name="LCHARG"> F  </i>
   <i type="logical" name="LPARD"> F  </i>
   <i type="logical" name="LVTOT"> F  </i>
   <i type="logical" name="LVHAR"> F  </i>
   <i type="logical" name="LELF"> F  </i>
   <i type="logical" name="LOPTICS"> F  </i>
   <v name="STM">      0.00000000      0.00000000      0.00000000      0.00000000      0.00000000      0.00000000      0.00000000</v>
  </separator>
  <separator name="performance" >
   <i type="int" name="NPAR">     8</i>
   <i type="int" name="NSIM">     4</i>
   <i type="int" name="NBLK">    -1</i>
   <i type="logical" name="LPLANE"> T  </i>
   <i type="logical" name="LSCALAPACK"> T  </i>
   <i type="logical" name="LSCAAWARE"> F  </i>
   <i type="logical" name="LSCALU"> F  </i>
   <i type="logical" name="LASYNC"> F  </i>
   <i type="logical" name="LORBITALREAL"> F  </i>
  </separator>
  <separator name="miscellaneous" >
   <i type="int" name="IDIOT">     3</i>
   <i type="int" name="ISPECIAL">     0</i>
   <i type="logical" name="LMUSIC"> F  </i>
   <v name="POMASS">     28.08500000     16.00000000</v>
   <v name="DARWINR">      0.00000000      0.00000000</v>
   <v name="DARWINV">      1.00000000      1.00000000</v>
   <i type="logical" name="LCORR"> T  </i>
  </separator>
  <i type="logical" name="GGA_COMPAT"> T  </i>
  <i type="logical" name="LBERRY"> F  </i>
  <i type="int" name="ICORELEVEL">     0</i>
  <i type="logical" name="LDAU"> F  </i>
  <i type="int" name="I_CONSTRAINED_M">     0</i>
  <separator name="electronic exchange-correlation" >
   <i type="string" name="GGA">--</i>
   <i type="int" name="VOSKOWN">     0</i>
   <i type="logical" name="LHFCALC"> F  </i>
   <i type="string" name="PRECFOCK"></i>
   <i type="logical" name="LSYMGRAD"> F  </i>
   <i type="logical" name="LHFONE"> F  </i>
   <i type="logical" name="LRHFCALC"> F  </i>
   <i type="logical" name="LTHOMAS"> F  </i>
   <i type="logical" name="LMODELHF"> F  </i>
   <i name="ENCUT4O">     -1.00000000</i>
   <i type="int" name="EXXOEP">     0</i>
   <i type="int" name="FOURORBIT">     0</i>
   <i name="AEXX">      0.00000000</i>
   <i name="HFALPHA">      0.00000000</i>
   <i name="MCALPHA">      0.00000000</i>
   <i name="ALDAX">      1.00000000</i>
   <i name="AGGAX">      1.00000000</i>
   <i name="ALDAC">      1.00000000</i>
   <i name="AGGAC">      1.00000000</i>
   <i type="int" name="NKREDX">     1</i>
   <i type="int" name="NKREDY">     1</i>
   <i type="int" name="NKREDZ">     1</i>
   <i type="logical" name="SHIFTRED"> F  </i>
   <i type="logical" name="ODDONLY"> F  </i>
   <i type="logical" name="EVENONLY"> F  </i>
   <i type="int" name="LMAXFOCK">     0</i>
   <i type="int" name="NMAXFOCKAE">     0</i>
   <i type="logical" name="LFOCKAEDFT"> F  </i>
   <i name="HFSCREEN">      0.00000000</i>
   <i name="HFSCREENC">      0.00000000</i>
   <i type="int" name="NBANDSGWLOW">     0</i>
  </separator>
  <separator name="vdW DFT" >
   <i type="logical" name="LUSE_VDW"> F  </i>
   <i name="Zab_VDW">     -0.84910000</i>
   <i name="PARAM1">      0.12340000</i>
   <i name="PARAM2">      1.00000000</i>
   <i name="PARAM3">      0.00000000</i>
  </separator>
  <separator name="model GW" >
   <i type="int" name="MODEL_GW">     0</i>
   <i name="MODEL_EPS0">      8.82060104</i>
   <i name="MODEL_ALPHA">      1.00000000</i>
  </separator>
  <separator name="linear response parameters" >
   <i type="logical" name="LEPSILON"> F  </i>
   <i type="logical" name="LRPA"> F  </i>
   <i type="logical" name="LNABLA"> F  </i>
   <i type="logical" name="LVEL"> F  </i>
   <i type="int" name="KINTER">     0</i>
   <i name="CSHIFT">      0.10000000</i>
   <i name="OMEGAMAX">     -1.00000000</i>
   <i name="DEG_THRESHOLD">      0.00200000</i>
   <i name="RTIME">     -0.10000000</i>
   <i name="WPLASMAI">      0.00000000</i>
   <v name="DFIELD">      0.00000000      0.00000000      0.00000000</v>
   <v name="WPLASMA">      0.00000000      0.00000000      0.00000000      0.00000000      0.00000000      0.00000000      0.00000000      0.00000000      0.00000000</v>
  </separator>
  <separator name="orbital magnetization" >
   <i type="logical" name="NUCIND"> F  </i>
   <v name="MAGPOS">      0.00000000      0.00000000      0.00000000</v>
   <i type="logical" name="LNICSALL"> T  </i>
   <i type="logical" name="ORBITALMAG"> F  </i>
   <i type="logical" name="LMAGBLOCH"> F  </i>
   <i type="logical" name="LCHIMAG"> F  </i>
   <i type="logical" name="LGAUGE"> T  </i>
   <i type="int" name="MAGATOM">     0</i>
   <v name="MAGDIPOL">      0.00000000      0.00000000      0.00000000</v>
   <v name="AVECCONST">      0.00000000      0.00000000      0.00000000</v>
  </separator>
  <separator name="response functions" >
   <i type="logical" name="LADDER"> F  </i>
   <i type="logical" name="LRPAFORCE"> F  </i>
   <i type="logical" name="LFXC"> F  </i>
   <i type="logical" name="LHARTREE"> T  </i>
   <i type="int" name="IBSE">     0</i>
   <v type="int" name="KPOINT">    -1     0     0     0</v>
   <i type="logical" name="LTCTE"> F  </i>
   <i type="logical" name="LTETE"> F  </i>
   <i type="logical" name="LTRIPLET"> F  </i>
   <i type="logical" name="LFXCEPS"> F  </i>
   <i type="logical" name="LFXHEG"> F  </i>
   <i type="int" name="NATURALO">     2</i>
   <i type="logical" name="L2ORDER"> F  </i>
   <i type="logical" name="LMP2LT"> F  </i>
   <i type="logical" name="LUSEW"> F  </i>
   <i name="ENCUTGW">     -2.00000000</i>
   <i name="ENCUTGWSOFT">     -2.00000000</i>
   <i name="ENCUTLF">     -1.00000000</i>
   <i type="int" name="LMAXMP2">    -1</i>
   <i name="SCISSOR">      0.00000000</i>
   <i type="int" name="NOMEGA">     0</i>
   <i type="int" name="NOMEGAR">     0</i>
   <i type="int" name="NBANDSGW">    -1</i>
   <i type="int" name="NBANDSO">    -1</i>
   <i type="int" name="NBANDSV">    -1</i>
   <i type="int" name="NELM">     1</i>
   <i type="int" name="NELMHF">     1</i>
   <i type="int" name="DIM">     3</i>
   <i type="int" name="ANTIRES">     0</i>
   <i name="OMEGAMAX">    -30.00000000</i>
   <i name="OMEGAMIN">    -30.00000000</i>
   <i name="OMEGATL">   -200.00000000</i>
   <i type="int" name="OMEGAGRID">   140</i>
   <i name="CSHIFT">     -0.10000000</i>
   <i type="logical" name="SELFENERGY"> F  </i>
   <i type="logical" name="LSPECTRAL"> F  </i>
   <i type="logical" name="LSPECTRALGW"> F  </i>
   <i type="logical" name="LSINGLES"> F  </i>
   <i type="logical" name="LFERMIGW"> F  </i>
   <i type="logical" name="ODDONLYGW"> F  </i>
   <i type="logical" name="EVENONLYGW"> F  </i>
   <i type="int" name="NKREDLFX">     1</i>
   <i type="int" name="NKREDLFY">     1</i>
   <i type="int" name="NKREDLFZ">     1</i>
   <i type="int" name="MAXMEM">  2800</i>
   <i type="int" name="TELESCOPE">     0</i>
   <i type="int" name="TAUPAR">     1</i>
   <i type="int" name="OMEGAPAR">    -1</i>
   <i name="LAMBDA">      1.00000000</i>
  </separator>
  <separator name="External order field" >
   <i name="OFIELD_KAPPA">      0.00000000</i>
   <v name="OFIELD_K">      0.00000000      0.00000000      0.00000000</v>
   <i name="OFIELD_Q6_NEAR">      0.00000000</i>
   <i name="OFIELD_Q6_FAR">      0.00000000</i>
   <i name="OFIELD_A">      0.00000000</i>
  </separator>
 </parameters>
 <atominfo>
  <atoms>      15 </atoms>
  <types>       2 </types>
  <array name="atoms" >
   <dimension dim="1">ion</dimension>
   <field type="string">element</field>
   <field type="int">atomtype</field>
   <set>
    <rc><c>Si</c><c>   1</c></rc>
    <rc><c>Si</c><c>   1</c></rc>
    <rc><c>Si</c><c>   1</c></rc>
    <rc><c>Si</c><c>   1</c></rc>
    <rc><c>Si</c><c>   1</c></rc>
    <rc><c>Si</c><c>   1</c></rc>
    <rc><c>Si</c><c>   1</c></rc>
    <rc><c>Si</c><c>   1</c></rc>
    <rc><c>Si</c><c>   1</c></rc>
    <rc><c>Si</c><c>   1</c></rc>
    <rc><c>O </c><c>   2</c></rc>
    <rc><c>O </c><c>   2</c></rc>
    <rc><c>O </c><c>   2</c></rc>
    <rc><c>O </c><c>   2</c></rc>
    <rc><c>O </c><c>   2</c></rc>
   </set>
  </array>
  <array name="atomtypes" >
   <dimension dim="1">type</dimension>
   <field type="int">atomspertype</field>
   <field type="string">element</field>
   <field>mass</field>
   <field>valence</field>
   <field type="string">pseudopotential</field>
   <set>
    <rc><c>  10</c><c>Si</c><c>     28.08500000</c><c>      4.00000000</c><c>  PAW_PBE Si 05Jan2001                  </c></rc>
    <rc><c>   5</c><c>O </c><c>     16.00000000</c><c>      6.00000000</c><c>  PAW_PBE O 08Apr2002                   </c></rc>
   </set>
  </array>
 </atominfo>
 <structure name="initialpos" >
  <crystal>
   <varray name="basis" >
    <v>       6.12463900       0.07338700       0.11643400 </v>
    <v>       0.10284100       6.12337600       0.21606000 </v>
    <v>       0.22619200       0.19802000       5.89217100 </v>
   </varray>
   <i name="volume">    220.51502595 </i>
   <varray name="rec_basis" >
    <v>       0.16342285      -0.00252629      -0.00618867 </v>
    <v>      -0.00185635       0.16353119      -0.00542458 </v>
    <v>      -0.00316130      -0.00594660       0.17003794 </v>
   </varray>
  </crystal>
  <varray name="positions" >
   <v>       0.24546400       0.23212500       0.23084700 </v>
   <v>       0.80047100       0.80006400       0.19867800 </v>
   <v>       0.81033100       0.17152300       0.80891400 </v>
   <v>       0.18090500       0.81913800       0.82178900 </v>
   <v>       0.34804700       0.47449400       0.92751700 </v>
   <v>       0.72514900       0.50278200       0.98477200 </v>
   <v>       0.45032700       0.92236300       0.34010900 </v>
   <v>       0.93168800       0.32030900       0.44130700 </v>
   <v>       0.00404300       0.69071400       0.51642700 </v>
   <v>       0.46317000       0.06007600       0.71053100 </v>
   <v>       0.96063700       0.96847700       0.98190400 </v>
   <v>       0.72040100       0.33498400       0.27410200 </v>
   <v>       0.27475100       0.71797200       0.34199700 </v>
   <v>       0.33859400       0.31511100       0.70081800 </v>
   <v>       0.76636700       0.65686500       0.71529900 </v>
  </varray>
 </structure>
 <calculation>
  <scstep>
   <time name="dav">    1.18    1.19</time>
   <time name="total">    1.21    1.23</time>
   <energy>
    <i name="alphaZ">     63.47288322 </i>
    <i name="ewald">  -2557.95807118 </i>
    <i name="hartreedc">   -840.89633131 </i>
    <i name="XCdc">     47.90731230 </i>
    <i name="pawpsdc">   2613.98538060 </i>
    <i name="pawaedc">  -2447.04591568 </i>
    <i name="eentropy">     -0.00454038 </i>
    <i name="bandstr">    242.22817144 </i>
    <i name="atom">   3192.47549744 </i>
    <i name="e_fr_energy">    314.16438644 </i>
    <i name="e_wo_entrp">    314.16892682 </i>
    <i name="e_0_energy">    314.16589990 </i>
   </energy>
  </scstep>
  <scstep>
   <time name="dav">    1.27    1.27</time>
   <time name="total">    1.27    1.27</time>
   <energy>
    <i name="e_fr_energy">    -64.62868564 </i>
    <i name="e_wo_entrp">    -64.62958116 </i>
    <i name="e_0_energy">    -64.62898415 </i>
   </energy>
  </scstep>
  <scstep>
   <time name="dav">    1.37    1.38</time>
   <time name="total">    1.37    1.38</time>
   <energy>
    <i name="e_fr_energy">    -97.14933804 </i>
    <i name="e_wo_entrp">    -97.15004889 </i>
    <i name="e_0_energy">    -97.14957499 </i>
   </energy>
  </scstep>
  <scstep>
   <time name="dav">    1.25    1.26</time>
   <time name="total">    1.25    1.26</time>
   <energy>
    <i name="e_fr_energy">    -97.75526279 </i>
    <i name="e_wo_entrp">    -97.75597834 </i>
    <i name="e_0_energy">    -97.75550131 </i>
   </energy>
  </scstep>
  <scstep>
   <time name="dav">    1.24    1.24</time>
   <time name="total">    1.31    1.31</time>
   <energy>
    <i name="e_fr_energy">    -97.76487166 </i>
    <i name="e_wo_entrp">    -97.76558785 </i>
    <i name="e_0_energy">    -97.76511039 </i>
   </energy>
  </scstep>
  <scstep>
   <time name="dav">    1.22    1.22</time>
   <time name="total">    1.34    1.34</time>
   <energy>
    <i name="e_fr_energy">    -90.23368220 </i>
    <i name="e_wo_entrp">    -90.23432184 </i>
    <i name="e_0_energy">    -90.23389542 </i>
   </energy>
  </scstep>
  <scstep>
   <time name="dav">    1.19    1.19</time>
   <time name="total">    1.33    1.33</time>
   <energy>
    <i name="e_fr_energy">    -90.17009547 </i>
    <i name="e_wo_entrp">    -90.16962859 </i>
    <i name="e_0_energy">    -90.16993984 </i>
   </energy>
  </scstep>
  <scstep>
   <time name="dav">    1.20    1.20</time>
   <time name="total">    1.33    1.34</time>
   <energy>
    <i name="e_fr_energy">    -90.08896741 </i>
    <i name="e_wo_entrp">    -90.08799520 </i>
    <i name="e_0_energy">    -90.08864334 </i>
   </energy>
  </scstep>
  <scstep>
   <time name="dav">    1.30    1.30</time>
   <time name="total">    1.44    1.44</time>
   <energy>
    <i name="e_fr_energy">    -90.04858890 </i>
    <i name="e_wo_entrp">    -90.04950650 </i>
    <i name="e_0_energy">    -90.04889477 </i>
   </energy>
  </scstep>
  <scstep>
   <time name="dav">    1.20    1.20</time>
   <time name="total">    1.34    1.34</time>
   <energy>
    <i name="e_fr_energy">    -90.05039680 </i>
    <i name="e_wo_entrp">    -90.05062131 </i>
    <i name="e_0_energy">    -90.05047164 </i>
   </energy>
  </scstep>
  <scstep>
   <time name="dav">    1.23    1.23</time>
   <time name="total">    1.37    1.38</time>
   <energy>
    <i name="e_fr_energy">    -90.05100748 </i>
    <i name="e_wo_entrp">    -90.05123809 </i>
    <i name="e_0_energy">    -90.05108435 </i>
   </energy>
  </scstep>
  <scstep>
   <time name="dav">    1.35    1.35</time>
   <time name="total">    1.50    1.50</time>
   <energy>
    <i name="e_fr_energy">    -90.05113390 </i>
    <i name="e_wo_entrp">    -90.05138063 </i>
    <i name="e_0_energy">    -90.05121614 </i>
   </energy>
  </scstep>
  <scstep>
   <time name="dav">    1.22    1.22</time>
   <time name="total">    1.36    1.36</time>
   <energy>
    <i name="e_fr_energy">    -90.05119324 </i>
    <i name="e_wo_entrp">    -90.05144783 </i>
    <i name="e_0_energy">    -90.05127811 </i>
   </energy>
  </scstep>
  <scstep>
   <time name="dav">    0.99    1.00</time>
   <time name="total">    1.13    1.13</time>
   <energy>
    <i name="e_fr_energy">    -90.05120424 </i>
    <i name="e_wo_entrp">    -90.05144529 </i>
    <i name="e_0_energy">    -90.05128459 </i>
   </energy>
  </scstep>
  <scstep>
   <time name="dav">    0.86    0.86</time>
   <time name="total">    0.89    0.89</time>
   <energy>
    <i name="alphaZ">     63.47288322 </i>
    <i name="ewald">  -2557.95807118 </i>
    <i name="hartreedc">   -938.77168194 </i>
    <i name="XCdc">     55.31843074 </i>
    <i name="pawpsdc">   7107.72155087 </i>
    <i name="pawaedc">  -6942.38639080 </i>
    <i name="eentropy">      0.00023370 </i>
    <i name="bandstr">    -69.92365991 </i>
    <i name="atom">   3192.47549744 </i>
    <i name="e_fr_energy">    -90.05120786 </i>
    <i name="e_wo_entrp">    -90.05144156 </i>
    <i name="e_0_energy">    -90.05128576 </i>
   </energy>
  </scstep>
  <structure>
   <crystal>
    <varray name="basis" >
     <v>       6.12463900       0.07338700       0.11643400 </v>
     <v>       0.10284100       6.12337600       0.21606000 </v>
     <v>       0.22619200       0.19802000       5.89217100 </v>
    </varray>
    <i name="volume">    220.51502595 </i>
    <varray name="rec_basis" >
     <v>       0.16342285      -0.00252629      -0.00618867 </v>
     <v>      -0.00185635       0.16353119      -0.00542458 </v>
     <v>      -0.00316130      -0.00594660       0.17003794 </v>
    </varray>
   </crystal>
   <varray name="positions" >
    <v>       0.24546400       0.23212500       0.23084700 </v>
    <v>       0.80047100       0.80006400       0.19867800 </v>
    <v>       0.81033100       0.17152300       0.80891400 </v>
    <v>       0.18090500       0.81913800       0.82178900 </v>
    <v>       0.34804700       0.47449400       0.92751700 </v>
    <v>       0.72514900       0.50278200       0.98477200 </v>
    <v>       0.45032700       0.92236300       0.34010900 </v>
    <v>       0.93168800       0.32030900       0.44130700 </v>
    <v>       0.00404300       0.69071400       0.51642700 </v>
    <v>       0.46317000       0.06007600       0.71053100 </v>
    <v>       0.96063700       0.96847700       0.98190400 </v>
    <v>       0.72040100       0.33498400       0.27410200 </v>
    <v>       0.27475100       0.71797200       0.34199700 </v>
    <v>       0.33859400       0.31511100       0.70081800 </v>
    <v>       0.76636700       0.65686500       0.71529900 </v>
   </varray>
  </structure>
  <varray name="forces" >
   <v>      -0.00585744      -0.00263812      -0.00509882 </v>
   <v>      -0.00657348      -0.02703016       0.00976448 </v>
   <v>      -0.00579045      -0.01462697      -0.00045019 </v>
   <v>      -0.00698984       0.01001789      -0.00747863 </v>
   <v>       0.00763207       0.03093933       0.02583235 </v>
   <v>       0.00908506      -0.00884169      -0.01381247 </v>
   <v>       0.00472079       0.01756860       0.00013854 </v>
   <v>      -0.01077115      -0.02698611      -0.01119275 </v>
   <v>       0.01379935      -0.00831632      -0.00839150 </v>
   <v>      -0.01345260       0.03026504       0.00559759 </v>
   <v>      -0.01183910      -0.00892423      -0.00688650 </v>
   <v>      -0.00451538      -0.01136311       0.00273956 </v>
   <v>       0.00821605       0.01028459       0.00924890 </v>
   <v>       0.01100027       0.03704641       0.01884503 </v>
   <v>       0.01133584      -0.02739516      -0.01885559 </v>
  </varray>
  <varray name="stress" >
   <v>       0.25548036      -0.03454327       0.04777852 </v>
   <v>      -0.03454324       0.40605369       0.11461934 </v>
   <v>       0.04777847       0.11461941      -0.23166525 </v>
  </varray>
  <energy>
   <i name="e_fr_energy">    -90.05120786 </i>
   <i name="e_wo_entrp">    -90.05128576 </i>
   <i name="e_0_energy">      0.00023370 </i>
  </energy>
  <time name="totalsc">   21.37   21.45</time>
  <eigenvalues>
   <array>
    <dimension dim="1">band</dimension>
    <dimension dim="2">kpoint</dimension>
    <dimension dim="3">spin</dimension>
    <field>eigene</field>
    <field>occ</field>
    <set>
     <set comment="spin 1">
      <set comment="kpoint 1">
       <r>  -15.4137    1.0000 </r>
       <r>  -13.9389    1.0000 </r>
       <r>  -13.0702    1.0000 </r>
       <r>  -12.9200    1.0000 </r>
       <r>  -12.4622    1.0000 </r>
       <r>   -3.9018    1.0000 </r>
       <r>   -3.7891    1.0000 </r>
       <r>   -3.6754    1.0000 </r>
       <r>   -3.4624    1.0000 </r>
       <r>   -3.2175    1.0000 </r>
       <r>   -2.3108    1.0000 </r>
       <r>   -1.7106    1.0000 </r>
       <r>   -1.2546    1.0000 </r>
       <r>   -0.9037    1.0000 </r>
       <r>   -0.4712    1.0000 </r>
       <r>   -0.1070    1.0000 </r>
       <r>    0.1181    1.0000 </r>
       <r>    0.4726    1.0000 </r>
       <r>    0.6775    1.0000 </r>
       <r>    1.2547    1.0000 </r>
       <r>    1.4936    1.0000 </r>
       <r>    1.6773    1.0000 </r>
       <r>    2.0003    1.0000 </r>
       <r>    2.3296    1.0000 </r>
       <r>    2.5883    1.0000 </r>
       <r>    3.0592    1.0000 </r>
       <r>    3.5472    1.0000 </r>
       <r>    3.8532    1.0000 </r>
       <r>    4.0397    1.0000 </r>
       <r>    4.1832    1.0000 </r>
       <r>    4.6988    1.0000 </r>
       <r>    4.8843    1.0000 </r>
       <r>    5.2614    1.0000 </r>
       <r>    5.4188    1.0000 </r>
       <r>    5.8748    1.0037 </r>
       <r>    7.1347   -0.0000 </r>
       <r>    8.2664   -0.0000 </r>
       <r>    8.4444   -0.0000 </r>
       <r>    8.4658   -0.0000 </r>
       <r>    8.6856   -0.0000 </r>
       <r>    9.2921    0.0000 </r>
       <r>    9.5286    0.0000 </r>
       <r>    9.6763    0.0000 </r>
       <r>    9.8815    0.0000 </r>
       <r>   10.5189    0.0000 </r>
       <r>   10.8284    0.0000 </r>
       <r>   11.0465    0.0000 </r>
       <r>   11.2533    0.0000 </r>
      </set>
      <set comment="kpoint 2">
       <r>  -15.4114    1.0000 </r>
       <r>  -13.9367    1.0000 </r>
       <r>  -13.0490    1.0000 </r>
       <r>  -12.9405    1.0000 </r>
       <r>  -12.4660    1.0000 </r>
       <r>   -4.2679    1.0000 </r>
       <r>   -3.8940    1.0000 </r>
       <r>   -3.7293    1.0000 </r>
       <r>   -3.1970    1.0000 </r>
       <r>   -2.9974    1.0000 </r>
       <r>   -2.4117    1.0000 </r>
       <r>   -1.6450    1.0000 </r>
       <r>   -1.2817    1.0000 </r>
       <r>   -0.6656    1.0000 </r>
       <r>   -0.3648    1.0000 </r>
       <r>   -0.2969    1.0000 </r>
       <r>    0.1665    1.0000 </r>
       <r>    0.3449    1.0000 </r>
       <r>    0.9333    1.0000 </r>
       <r>    1.3053    1.0000 </r>
       <r>    1.6162    1.0000 </r>
       <r>    1.8596    1.0000 </r>
       <r>    2.1068    1.0000 </r>
       <r>    2.4729    1.0000 </r>
       <r>    2.6823    1.0000 </r>
       <r>    2.9702    1.0000 </r>
       <r>    3.2433    1.0000 </r>
       <r>    3.5769    1.0000 </r>
       <r>    3.9589    1.0000 </r>
       <r>    4.1330    1.0000 </r>
       <r>    4.5127    1.0000 </r>
       <r>    4.7740    1.0000 </r>
       <r>    5.2882    1.0000 </r>
       <r>    5.4701    1.0000 </r>
       <r>    5.9452    1.0269 </r>
       <r>    7.1315   -0.0000 </r>
       <r>    7.7992   -0.0000 </r>
       <r>    8.2652   -0.0000 </r>
       <r>    8.6751   -0.0000 </r>
       <r>    8.9256    0.0000 </r>
       <r>    9.3558    0.0000 </r>
       <r>    9.5261    0.0000 </r>
       <r>    9.7088    0.0000 </r>
       <r>    9.9648    0.0000 </r>
       <r>   10.4916    0.0000 </r>
       <r>   10.7090    0.0000 </r>
       <r>   11.0753    0.0000 </r>
       <r>   11.3547    0.0000 </r>
      </set>
      <set comment="kpoint 3">
       <r>  -15.4104    1.0000 </r>
       <r>  -13.9354    1.0000 </r>
       <r>  -13.0678    1.0000 </r>
       <r>  -12.9289    1.0000 </r>
       <r>  -12.4616    1.0000 </r>
       <r>   -4.1419    1.0000 </r>
       <r>   -4.0091    1.0000 </r>
       <r>   -3.6969    1.0000 </r>
       <r>   -3.3577    1.0000 </r>
       <r>   -3.0649    1.0000 </r>
       <r>   -2.1286    1.0000 </r>
       <r>   -1.5161    1.0000 </r>
       <r>   -1.3260    1.0000 </r>
       <r>   -0.8859    1.0000 </r>
       <r>   -0.4156    1.0000 </r>
       <r>   -0.2507    1.0000 </r>
       <r>    0.1027    1.0000 </r>
       <r>    0.5145    1.0000 </r>
       <r>    0.8545    1.0000 </r>
       <r>    1.3641    1.0000 </r>
       <r>    1.7012    1.0000 </r>
       <r>    1.7854    1.0000 </r>
       <r>    2.1101    1.0000 </r>
       <r>    2.3663    1.0000 </r>
       <r>    2.6944    1.0000 </r>
       <r>    3.0399    1.0000 </r>
       <r>    3.1582    1.0000 </r>
       <r>    3.5023    1.0000 </r>
       <r>    4.0051    1.0000 </r>
       <r>    4.0776    1.0000 </r>
       <r>    4.3855    1.0000 </r>
       <r>    4.9200    1.0000 </r>
       <r>    5.3784    1.0000 </r>
       <r>    5.6159    1.0000 </r>
       <r>    5.7787    1.0000 </r>
       <r>    7.2084   -0.0000 </r>
       <r>    7.9042   -0.0000 </r>
       <r>    8.4612   -0.0000 </r>
       <r>    8.6822   -0.0000 </r>
       <r>    8.8014   -0.0000 </r>
       <r>    9.0833    0.0000 </r>
       <r>    9.5269    0.0000 </r>
       <r>    9.6988    0.0000 </r>
       <r>   10.0511    0.0000 </r>
       <r>   10.3882    0.0000 </r>
       <r>   10.6811    0.0000 </r>
       <r>   11.0959    0.0000 </r>
       <r>   11.4761    0.0000 </r>
      </set>
      <set comment="kpoint 4">
       <r>  -15.4085    1.0000 </r>
       <r>  -13.9324    1.0000 </r>
       <r>  -13.0483    1.0000 </r>
       <r>  -12.9461    1.0000 </r>
       <r>  -12.4662    1.0000 </r>
       <r>   -4.4192    1.0000 </r>
       <r>   -4.0872    1.0000 </r>
       <r>   -3.8003    1.0000 </r>
       <r>   -3.1286    1.0000 </r>
       <r>   -2.7867    1.0000 </r>
       <r>   -2.3966    1.0000 </r>
       <r>   -1.6593    1.0000 </r>
       <r>   -1.1638    1.0000 </r>
       <r>   -0.5630    1.0000 </r>
       <r>   -0.3552    1.0000 </r>
       <r>   -0.1911    1.0000 </r>
       <r>    0.3603    1.0000 </r>
       <r>    0.6238    1.0000 </r>
       <r>    0.8859    1.0000 </r>
       <r>    1.3259    1.0000 </r>
       <r>    1.6326    1.0000 </r>
       <r>    1.8744    1.0000 </r>
       <r>    2.0755    1.0000 </r>
       <r>    2.3331    1.0000 </r>
       <r>    2.6112    1.0000 </r>
       <r>    2.8803    1.0000 </r>
       <r>    2.9976    1.0000 </r>
       <r>    3.4367    1.0000 </r>
       <r>    3.8829    1.0000 </r>
       <r>    4.1685    1.0000 </r>
       <r>    4.5408    1.0000 </r>
       <r>    4.7958    1.0000 </r>
       <r>    5.3081    1.0000 </r>
       <r>    5.6052    1.0000 </r>
       <r>    5.9561    1.0315 </r>
       <r>    6.9699   -0.0000 </r>
       <r>    7.6778   -0.0000 </r>
       <r>    8.1876   -0.0000 </r>
       <r>    8.6312   -0.0000 </r>
       <r>    8.9355    0.0000 </r>
       <r>    9.1906    0.0000 </r>
       <r>    9.3282    0.0000 </r>
       <r>    9.6097    0.0000 </r>
       <r>   10.0288    0.0000 </r>
       <r>   10.3735    0.0000 </r>
       <r>   10.6992    0.0000 </r>
       <r>   11.2078    0.0000 </r>
       <r>   11.3882    0.0000 </r>
      </set>
      <set comment="kpoint 5">
       <r>  -15.4085    1.0000 </r>
       <r>  -13.9322    1.0000 </r>
       <r>  -13.0529    1.0000 </r>
       <r>  -12.9407    1.0000 </r>
       <r>  -12.4674    1.0000 </r>
       <r>   -4.4288    1.0000 </r>
       <r>   -4.0779    1.0000 </r>
       <r>   -3.8056    1.0000 </r>
       <r>   -3.1823    1.0000 </r>
       <r>   -2.7730    1.0000 </r>
       <r>   -2.2364    1.0000 </r>
       <r>   -1.7974    1.0000 </r>
       <r>   -1.1419    1.0000 </r>
       <r>   -0.4957    1.0000 </r>
       <r>   -0.3017    1.0000 </r>
       <r>   -0.0140    1.0000 </r>
       <r>    0.1964    1.0000 </r>
       <r>    0.5098    1.0000 </r>
       <r>    0.8252    1.0000 </r>
       <r>    1.1402    1.0000 </r>
       <r>    1.5367    1.0000 </r>
       <r>    2.0126    1.0000 </r>
       <r>    2.1718    1.0000 </r>
       <r>    2.3407    1.0000 </r>
       <r>    2.6403    1.0000 </r>
       <r>    2.7410    1.0000 </r>
       <r>    3.2083    1.0000 </r>
       <r>    3.4646    1.0000 </r>
       <r>    3.8410    1.0000 </r>
       <r>    4.1115    1.0000 </r>
       <r>    4.4140    1.0000 </r>
       <r>    4.9673    1.0000 </r>
       <r>    5.1930    1.0000 </r>
       <r>    5.8057    1.0002 </r>
       <r>    6.1052    0.4293 </r>
       <r>    7.0080   -0.0000 </r>
       <r>    7.5962   -0.0000 </r>
       <r>    8.1321   -0.0000 </r>
       <r>    8.6324   -0.0000 </r>
       <r>    8.8673    0.0000 </r>
       <r>    8.9831    0.0000 </r>
       <r>    9.3538    0.0000 </r>
       <r>    9.7301    0.0000 </r>
       <r>   10.1292    0.0000 </r>
       <r>   10.3215    0.0000 </r>
       <r>   10.8013    0.0000 </r>
       <r>   10.9025    0.0000 </r>
       <r>   11.3561    0.0000 </r>
      </set>
      <set comment="kpoint 6">
       <r>  -15.4105    1.0000 </r>
       <r>  -13.9336    1.0000 </r>
       <r>  -13.0644    1.0000 </r>
       <r>  -12.9076    1.0000 </r>
       <r>  -12.4879    1.0000 </r>
       <r>   -4.2449    1.0000 </r>
       <r>   -3.8759    1.0000 </r>
       <r>   -3.7886    1.0000 </r>
       <r>   -3.3671    1.0000 </r>
       <r>   -2.9343    1.0000 </r>
       <r>   -2.3965    1.0000 </r>
       <r>   -1.6905    1.0000 </r>
       <r>   -1.3557    1.0000 </r>
       <r>   -0.5751    1.0000 </r>
       <r>   -0.3279    1.0000 </r>
       <r>   -0.0886    1.0000 </r>
       <r>    0.1235    1.0000 </r>
       <r>    0.6840    1.0000 </r>
       <r>    0.9020    1.0000 </r>
       <r>    1.1732    1.0000 </r>
       <r>    1.3870    1.0000 </r>
       <r>    2.0161    1.0000 </r>
       <r>    2.2136    1.0000 </r>
       <r>    2.3468    1.0000 </r>
       <r>    2.6644    1.0000 </r>
       <r>    2.9819    1.0000 </r>
       <r>    3.1267    1.0000 </r>
       <r>    3.5245    1.0000 </r>
       <r>    3.9224    1.0000 </r>
       <r>    4.2326    1.0000 </r>
       <r>    4.7692    1.0000 </r>
       <r>    4.9789    1.0000 </r>
       <r>    5.0812    1.0000 </r>
       <r>    5.3707    1.0000 </r>
       <r>    5.6277    1.0000 </r>
       <r>    7.0786   -0.0000 </r>
       <r>    7.9566   -0.0000 </r>
       <r>    8.5151   -0.0000 </r>
       <r>    8.7607   -0.0000 </r>
       <r>    8.9691    0.0000 </r>
       <r>    9.1800    0.0000 </r>
       <r>    9.4823    0.0000 </r>
       <r>    9.8392    0.0000 </r>
       <r>   10.0077    0.0000 </r>
       <r>   10.4244    0.0000 </r>
       <r>   10.8511    0.0000 </r>
       <r>   10.9949    0.0000 </r>
       <r>   11.4917    0.0000 </r>
      </set>
      <set comment="kpoint 7">
       <r>  -15.4087    1.0000 </r>
       <r>  -13.9316    1.0000 </r>
       <r>  -13.0513    1.0000 </r>
       <r>  -12.9171    1.0000 </r>
       <r>  -12.4917    1.0000 </r>
       <r>   -4.4145    1.0000 </r>
       <r>   -4.1614    1.0000 </r>
       <r>   -3.7912    1.0000 </r>
       <r>   -3.2755    1.0000 </r>
       <r>   -2.7388    1.0000 </r>
       <r>   -2.2512    1.0000 </r>
       <r>   -1.7882    1.0000 </r>
       <r>   -1.1426    1.0000 </r>
       <r>   -0.5917    1.0000 </r>
       <r>   -0.5093    1.0000 </r>
       <r>    0.1417    1.0000 </r>
       <r>    0.4395    1.0000 </r>
       <r>    0.8780    1.0000 </r>
       <r>    1.0083    1.0000 </r>
       <r>    1.2884    1.0000 </r>
       <r>    1.3188    1.0000 </r>
       <r>    1.8769    1.0000 </r>
       <r>    2.0569    1.0000 </r>
       <r>    2.3166    1.0000 </r>
       <r>    2.5431    1.0000 </r>
       <r>    2.8382    1.0000 </r>
       <r>    3.1452    1.0000 </r>
       <r>    3.4502    1.0000 </r>
       <r>    3.8045    1.0000 </r>
       <r>    4.2430    1.0000 </r>
       <r>    4.6644    1.0000 </r>
       <r>    4.8465    1.0000 </r>
       <r>    5.3024    1.0000 </r>
       <r>    5.5820    1.0000 </r>
       <r>    5.7544    1.0000 </r>
       <r>    6.8058   -0.0000 </r>
       <r>    7.7531   -0.0000 </r>
       <r>    8.2266   -0.0000 </r>
       <r>    8.7134   -0.0000 </r>
       <r>    8.8735    0.0000 </r>
       <r>    9.2637    0.0000 </r>
       <r>    9.3924    0.0000 </r>
       <r>    9.6264    0.0000 </r>
       <r>   10.0179    0.0000 </r>
       <r>   10.2271    0.0000 </r>
       <r>   10.5746    0.0000 </r>
       <r>   10.9419    0.0000 </r>
       <r>   11.4024    0.0000 </r>
      </set>
      <set comment="kpoint 8">
       <r>  -15.4086    1.0000 </r>
       <r>  -13.9318    1.0000 </r>
       <r>  -13.0462    1.0000 </r>
       <r>  -12.9221    1.0000 </r>
       <r>  -12.4924    1.0000 </r>
       <r>   -4.4278    1.0000 </r>
       <r>   -4.1841    1.0000 </r>
       <r>   -3.7098    1.0000 </r>
       <r>   -3.2070    1.0000 </r>
       <r>   -2.8962    1.0000 </r>
       <r>   -2.2026    1.0000 </r>
       <r>   -1.8136    1.0000 </r>
       <r>   -1.0928    1.0000 </r>
       <r>   -0.6043    1.0000 </r>
       <r>   -0.4225    1.0000 </r>
       <r>    0.1648    1.0000 </r>
       <r>    0.2459    1.0000 </r>
       <r>    0.8129    1.0000 </r>
       <r>    0.9168    1.0000 </r>
       <r>    1.2233    1.0000 </r>
       <r>    1.5041    1.0000 </r>
       <r>    1.7976    1.0000 </r>
       <r>    2.2191    1.0000 </r>
       <r>    2.3128    1.0000 </r>
       <r>    2.6897    1.0000 </r>
       <r>    2.9604    1.0000 </r>
       <r>    3.1152    1.0000 </r>
       <r>    3.2665    1.0000 </r>
       <r>    3.9063    1.0000 </r>
       <r>    4.0781    1.0000 </r>
       <r>    4.4324    1.0000 </r>
       <r>    4.9780    1.0000 </r>
       <r>    5.2858    1.0000 </r>
       <r>    5.6846    1.0000 </r>
       <r>    5.8919    1.0068 </r>
       <r>    6.8670   -0.0000 </r>
       <r>    7.6963   -0.0000 </r>
       <r>    8.2650   -0.0000 </r>
       <r>    8.7137   -0.0000 </r>
       <r>    8.9027    0.0000 </r>
       <r>    9.1077    0.0000 </r>
       <r>    9.2914    0.0000 </r>
       <r>    9.6019    0.0000 </r>
       <r>    9.7798    0.0000 </r>
       <r>   10.3746    0.0000 </r>
       <r>   10.7361    0.0000 </r>
       <r>   10.9853    0.0000 </r>
       <r>   11.4140    0.0000 </r>
      </set>
      <set comment="kpoint 9">
       <r>  -15.4078    1.0000 </r>
       <r>  -13.9302    1.0000 </r>
       <r>  -13.0605    1.0000 </r>
       <r>  -12.9156    1.0000 </r>
       <r>  -12.4873    1.0000 </r>
       <r>   -4.4292    1.0000 </r>
       <r>   -4.2302    1.0000 </r>
       <r>   -3.7266    1.0000 </r>
       <r>   -3.1156    1.0000 </r>
       <r>   -2.7364    1.0000 </r>
       <r>   -2.3174    1.0000 </r>
       <r>   -1.7914    1.0000 </r>
       <r>   -1.3968    1.0000 </r>
       <r>   -0.4418    1.0000 </r>
       <r>   -0.2439    1.0000 </r>
       <r>   -0.0714    1.0000 </r>
       <r>    0.3913    1.0000 </r>
       <r>    0.7071    1.0000 </r>
       <r>    0.8293    1.0000 </r>
       <r>    1.3633    1.0000 </r>
       <r>    1.6026    1.0000 </r>
       <r>    1.8657    1.0000 </r>
       <r>    2.0496    1.0000 </r>
       <r>    2.2207    1.0000 </r>
       <r>    2.5312    1.0000 </r>
       <r>    3.0583    1.0000 </r>
       <r>    3.2914    1.0000 </r>
       <r>    3.3644    1.0000 </r>
       <r>    3.8293    1.0000 </r>
       <r>    4.2009    1.0000 </r>
       <r>    4.6503    1.0000 </r>
       <r>    5.0301    1.0000 </r>
       <r>    5.1549    1.0000 </r>
       <r>    5.3910    1.0000 </r>
       <r>    5.8455    1.0011 </r>
       <r>    6.7029   -0.0000 </r>
       <r>    7.9544   -0.0000 </r>
       <r>    8.1726   -0.0000 </r>
       <r>    8.5048   -0.0000 </r>
       <r>    8.7918   -0.0000 </r>
       <r>    9.1757    0.0000 </r>
       <r>    9.3856    0.0000 </r>
       <r>    9.6464    0.0000 </r>
       <r>    9.9947    0.0000 </r>
       <r>   10.4069    0.0000 </r>
       <r>   10.5880    0.0000 </r>
       <r>   11.0971    0.0000 </r>
       <r>   11.4110    0.0000 </r>
      </set>
      <set comment="kpoint 10">
       <r>  -15.4062    1.0000 </r>
       <r>  -13.9282    1.0000 </r>
       <r>  -13.0484    1.0000 </r>
       <r>  -12.9232    1.0000 </r>
       <r>  -12.4907    1.0000 </r>
       <r>   -4.4986    1.0000 </r>
       <r>   -4.3837    1.0000 </r>
       <r>   -4.0746    1.0000 </r>
       <r>   -2.9156    1.0000 </r>
       <r>   -2.3290    1.0000 </r>
       <r>   -2.1192    1.0000 </r>
       <r>   -1.7705    1.0000 </r>
       <r>   -1.5296    1.0000 </r>
       <r>   -0.8155    1.0000 </r>
       <r>   -0.1437    1.0000 </r>
       <r>    0.0356    1.0000 </r>
       <r>    0.4777    1.0000 </r>
       <r>    0.8085    1.0000 </r>
       <r>    1.3317    1.0000 </r>
       <r>    1.4263    1.0000 </r>
       <r>    1.6545    1.0000 </r>
       <r>    1.8804    1.0000 </r>
       <r>    2.1619    1.0000 </r>
       <r>    2.2969    1.0000 </r>
       <r>    2.5279    1.0000 </r>
       <r>    2.7006    1.0000 </r>
       <r>    3.1747    1.0000 </r>
       <r>    3.5251    1.0000 </r>
       <r>    3.8186    1.0000 </r>
       <r>    4.2584    1.0000 </r>
       <r>    4.3704    1.0000 </r>
       <r>    4.6226    1.0000 </r>
       <r>    5.1244    1.0000 </r>
       <r>    5.5147    1.0000 </r>
       <r>    5.7815    1.0000 </r>
       <r>    6.1062    0.4211 </r>
       <r>    7.5355   -0.0000 </r>
       <r>    7.8813   -0.0000 </r>
       <r>    8.2745   -0.0000 </r>
       <r>    8.8103   -0.0000 </r>
       <r>    9.1091    0.0000 </r>
       <r>    9.3122    0.0000 </r>
       <r>   10.0691    0.0000 </r>
       <r>   10.2722    0.0000 </r>
       <r>   10.6054    0.0000 </r>
       <r>   11.0120    0.0000 </r>
       <r>   11.1334    0.0000 </r>
       <r>   11.6446    0.0000 </r>
      </set>
      <set comment="kpoint 11">
       <r>  -15.4062    1.0000 </r>
       <r>  -13.9281    1.0000 </r>
       <r>  -13.0467    1.0000 </r>
       <r>  -12.9238    1.0000 </r>
       <r>  -12.4927    1.0000 </r>
       <r>   -4.5773    1.0000 </r>
       <r>   -4.3440    1.0000 </r>
       <r>   -3.9935    1.0000 </r>
       <r>   -2.8368    1.0000 </r>
       <r>   -2.4711    1.0000 </r>
       <r>   -2.1926    1.0000 </r>
       <r>   -1.9419    1.0000 </r>
       <r>   -1.2190    1.0000 </r>
       <r>   -0.7266    1.0000 </r>
       <r>   -0.0847    1.0000 </r>
       <r>    0.2404    1.0000 </r>
       <r>    0.4642    1.0000 </r>
       <r>    0.6769    1.0000 </r>
       <r>    0.8824    1.0000 </r>
       <r>    1.3413    1.0000 </r>
       <r>    1.5242    1.0000 </r>
       <r>    1.8125    1.0000 </r>
       <r>    2.2377    1.0000 </r>
       <r>    2.3979    1.0000 </r>
       <r>    2.5797    1.0000 </r>
       <r>    3.0313    1.0000 </r>
       <r>    3.1487    1.0000 </r>
       <r>    3.4358    1.0000 </r>
       <r>    3.6699    1.0000 </r>
       <r>    3.9767    1.0000 </r>
       <r>    4.4959    1.0000 </r>
       <r>    4.7219    1.0000 </r>
       <r>    5.2837    1.0000 </r>
       <r>    5.6587    1.0000 </r>
       <r>    5.8442    1.0010 </r>
       <r>    6.3627   -0.0006 </r>
       <r>    7.5825   -0.0000 </r>
       <r>    8.0181   -0.0000 </r>
       <r>    8.3353   -0.0000 </r>
       <r>    8.7945   -0.0000 </r>
       <r>    9.0810    0.0000 </r>
       <r>    9.2647    0.0000 </r>
       <r>    9.6393    0.0000 </r>
       <r>    9.8710    0.0000 </r>
       <r>   10.3403    0.0000 </r>
       <r>   10.9682    0.0000 </r>
       <r>   11.2870    0.0000 </r>
       <r>   11.6556    0.0000 </r>
      </set>
      <set comment="kpoint 12">
       <r>  -15.4077    1.0000 </r>
       <r>  -13.9305    1.0000 </r>
       <r>  -13.0578    1.0000 </r>
       <r>  -12.9164    1.0000 </r>
       <r>  -12.4897    1.0000 </r>
       <r>   -4.4013    1.0000 </r>
       <r>   -4.1791    1.0000 </r>
       <r>   -3.7863    1.0000 </r>
       <r>   -3.2771    1.0000 </r>
       <r>   -2.7178    1.0000 </r>
       <r>   -2.2131    1.0000 </r>
       <r>   -1.6597    1.0000 </r>
       <r>   -1.3044    1.0000 </r>
       <r>   -0.5722    1.0000 </r>
       <r>   -0.3576    1.0000 </r>
       <r>    0.0883    1.0000 </r>
       <r>    0.2253    1.0000 </r>
       <r>    0.5288    1.0000 </r>
       <r>    0.9317    1.0000 </r>
       <r>    1.3831    1.0000 </r>
       <r>    1.5991    1.0000 </r>
       <r>    1.7700    1.0000 </r>
       <r>    2.2090    1.0000 </r>
       <r>    2.4942    1.0000 </r>
       <r>    2.5354    1.0000 </r>
       <r>    2.8822    1.0000 </r>
       <r>    3.0831    1.0000 </r>
       <r>    3.3501    1.0000 </r>
       <r>    3.9494    1.0000 </r>
       <r>    4.1597    1.0000 </r>
       <r>    4.4011    1.0000 </r>
       <r>    5.0902    1.0000 </r>
       <r>    5.3406    1.0000 </r>
       <r>    5.4965    1.0000 </r>
       <r>    5.9555    1.0313 </r>
       <r>    6.8405   -0.0000 </r>
       <r>    7.6774   -0.0000 </r>
       <r>    8.2088   -0.0000 </r>
       <r>    8.6095   -0.0000 </r>
       <r>    8.7834   -0.0000 </r>
       <r>    8.9333    0.0000 </r>
       <r>    9.4096    0.0000 </r>
       <r>    9.7881    0.0000 </r>
       <r>   10.0304    0.0000 </r>
       <r>   10.3165    0.0000 </r>
       <r>   10.7844    0.0000 </r>
       <r>   11.0579    0.0000 </r>
       <r>   11.3589    0.0000 </r>
      </set>
      <set comment="kpoint 13">
       <r>  -15.4062    1.0000 </r>
       <r>  -13.9281    1.0000 </r>
       <r>  -13.0503    1.0000 </r>
       <r>  -12.9183    1.0000 </r>
       <r>  -12.4948    1.0000 </r>
       <r>   -4.4830    1.0000 </r>
       <r>   -4.3176    1.0000 </r>
       <r>   -4.1629    1.0000 </r>
       <r>   -2.8013    1.0000 </r>
       <r>   -2.6470    1.0000 </r>
       <r>   -2.1714    1.0000 </r>
       <r>   -1.5767    1.0000 </r>
       <r>   -1.1459    1.0000 </r>
       <r>   -0.9189    1.0000 </r>
       <r>   -0.2880    1.0000 </r>
       <r>    0.2846    1.0000 </r>
       <r>    0.4343    1.0000 </r>
       <r>    0.6236    1.0000 </r>
       <r>    1.2335    1.0000 </r>
       <r>    1.3410    1.0000 </r>
       <r>    1.6387    1.0000 </r>
       <r>    1.8030    1.0000 </r>
       <r>    1.9989    1.0000 </r>
       <r>    2.4120    1.0000 </r>
       <r>    2.5774    1.0000 </r>
       <r>    2.7812    1.0000 </r>
       <r>    3.0692    1.0000 </r>
       <r>    3.2960    1.0000 </r>
       <r>    3.8843    1.0000 </r>
       <r>    3.9552    1.0000 </r>
       <r>    4.5448    1.0000 </r>
       <r>    4.9353    1.0000 </r>
       <r>    5.1917    1.0000 </r>
       <r>    5.6270    1.0000 </r>
       <r>    5.9232    1.0170 </r>
       <r>    6.4519   -0.0000 </r>
       <r>    7.5572   -0.0000 </r>
       <r>    8.0216   -0.0000 </r>
       <r>    8.3987   -0.0000 </r>
       <r>    8.7633   -0.0000 </r>
       <r>    8.8893    0.0000 </r>
       <r>    9.4398    0.0000 </r>
       <r>    9.7862    0.0000 </r>
       <r>    9.9569    0.0000 </r>
       <r>   10.4396    0.0000 </r>
       <r>   10.8893    0.0000 </r>
       <r>   11.1497    0.0000 </r>
       <r>   11.5329    0.0000 </r>
      </set>
      <set comment="kpoint 14">
       <r>  -15.4061    1.0000 </r>
       <r>  -13.9284    1.0000 </r>
       <r>  -13.0444    1.0000 </r>
       <r>  -12.9238    1.0000 </r>
       <r>  -12.4955    1.0000 </r>
       <r>   -4.5035    1.0000 </r>
       <r>   -4.3458    1.0000 </r>
       <r>   -4.0878    1.0000 </r>
       <r>   -2.6857    1.0000 </r>
       <r>   -2.5920    1.0000 </r>
       <r>   -2.2916    1.0000 </r>
       <r>   -1.9302    1.0000 </r>
       <r>   -1.1595    1.0000 </r>
       <r>   -0.5370    1.0000 </r>
       <r>   -0.1626    1.0000 </r>
       <r>    0.0847    1.0000 </r>
       <r>    0.3305    1.0000 </r>
       <r>    0.6502    1.0000 </r>
       <r>    1.1536    1.0000 </r>
       <r>    1.4660    1.0000 </r>
       <r>    1.7121    1.0000 </r>
       <r>    1.8836    1.0000 </r>
       <r>    1.9952    1.0000 </r>
       <r>    2.2334    1.0000 </r>
       <r>    2.6560    1.0000 </r>
       <r>    2.9122    1.0000 </r>
       <r>    3.0500    1.0000 </r>
       <r>    3.2047    1.0000 </r>
       <r>    3.8859    1.0000 </r>
       <r>    4.0620    1.0000 </r>
       <r>    4.4241    1.0000 </r>
       <r>    4.7073    1.0000 </r>
       <r>    5.2271    1.0000 </r>
       <r>    5.7355    1.0000 </r>
       <r>    5.9611    1.0332 </r>
       <r>    6.3553   -0.0008 </r>
       <r>    7.5883   -0.0000 </r>
       <r>    7.9515   -0.0000 </r>
       <r>    8.4134   -0.0000 </r>
       <r>    8.9246    0.0000 </r>
       <r>    9.0666    0.0000 </r>
       <r>    9.3684    0.0000 </r>
       <r>    9.6838    0.0000 </r>
       <r>    9.8877    0.0000 </r>
       <r>   10.3627    0.0000 </r>
       <r>   10.9234    0.0000 </r>
       <r>   11.2500    0.0000 </r>
       <r>   11.4742    0.0000 </r>
      </set>
     </set>
    </set>
   </array>
  </eigenvalues>
  <separator name="orbital magnetization" >
   <v name="MAGDIPOLOUT">      0.00000000      0.00000000      0.00000000</v>
  </separator>
  <dos>
   <i name="efermi">      6.09680789 </i>
   <total>
    <array>
     <dimension dim="1">gridpoints</dimension>
     <dimension dim="2">spin</dimension>
     <field>energy</field>
     <field>total</field>
     <field>integrated</field>
     <set>
      <set comment="spin 1">
       <r>   -16.7672     0.0000     0.0000 </r>
       <r>   -16.6680     0.0000     0.0000 </r>
       <r>   -16.5687     0.0000     0.0000 </r>
       <r>   -16.4694     0.0000     0.0000 </r>
       <r>   -16.3702     0.0000     0.0000 </r>
       <r>   -16.2709    -0.0000    -0.0000 </r>
       <r>   -16.1717    -0.0000    -0.0000 </r>
       <r>   -16.0724    -0.0000    -0.0000 </r>
       <r>   -15.9732    -0.0000    -0.0000 </r>
       <r>   -15.8739    -0.0000    -0.0000 </r>
       <r>   -15.7747    -0.0000    -0.0000 </r>
       <r>   -15.6754    -0.0106    -0.0011 </r>
       <r>   -15.5762    -0.3833    -0.0391 </r>
       <r>   -15.4769     1.3148     0.0914 </r>
       <r>   -15.3777    14.1322     1.4941 </r>
       <r>   -15.2784     5.7949     2.0693 </r>
       <r>   -15.1791    -0.6416     2.0056 </r>
       <r>   -15.0799    -0.0558     2.0000 </r>
       <r>   -14.9806    -0.0004     2.0000 </r>
       <r>   -14.8814    -0.0000     2.0000 </r>
       <r>   -14.7821    -0.0000     2.0000 </r>
       <r>   -14.6829    -0.0000     2.0000 </r>
       <r>   -14.5836    -0.0000     2.0000 </r>
       <r>   -14.4844    -0.0000     2.0000 </r>
       <r>   -14.3851    -0.0000     2.0000 </r>
       <r>   -14.2859    -0.0001     2.0000 </r>
       <r>   -14.1866    -0.0187     1.9981 </r>
       <r>   -14.0873    -0.4855     1.9499 </r>
       <r>   -13.9881     2.4549     2.1936 </r>
       <r>   -13.8888    14.7212     3.6548 </r>
       <r>   -13.7896     4.1024     4.0619 </r>
       <r>   -13.6903    -0.5896     4.0034 </r>
       <r>   -13.5911    -0.0342     4.0000 </r>
       <r>   -13.4918    -0.0002     4.0000 </r>
       <r>   -13.3926    -0.0002     4.0000 </r>
       <r>   -13.2933    -0.0380     3.9962 </r>
       <r>   -13.1941    -0.6009     3.9366 </r>
       <r>   -13.0948     3.9753     4.3311 </r>
       <r>   -12.9955    15.8243     5.9018 </r>
       <r>   -12.8963    16.1143     7.5012 </r>
       <r>   -12.7970     5.7238     8.0693 </r>
       <r>   -12.6978    -0.7358     7.9962 </r>
       <r>   -12.5985    -0.6030     7.9364 </r>
       <r>   -12.4993     7.9977     8.7302 </r>
       <r>   -12.4000    12.5757     9.9784 </r>
       <r>   -12.3008     0.5036    10.0284 </r>
       <r>   -12.2015    -0.2795    10.0006 </r>
       <r>   -12.1023    -0.0064    10.0000 </r>
       <r>   -12.0030    -0.0000    10.0000 </r>
       <r>   -11.9038    -0.0000    10.0000 </r>
       <r>   -11.8045    -0.0000    10.0000 </r>
       <r>   -11.7052     0.0000    10.0000 </r>
       <r>   -11.6060     0.0000    10.0000 </r>
       <r>   -11.5067     0.0000    10.0000 </r>
       <r>   -11.4075     0.0000    10.0000 </r>
       <r>   -11.3082     0.0000    10.0000 </r>
       <r>   -11.2090     0.0000    10.0000 </r>
       <r>   -11.1097     0.0000    10.0000 </r>
       <r>   -11.0105     0.0000    10.0000 </r>
       <r>   -10.9112     0.0000    10.0000 </r>
       <r>   -10.8120     0.0000    10.0000 </r>
       <r>   -10.7127     0.0000    10.0000 </r>
       <r>   -10.6134     0.0000    10.0000 </r>
       <r>   -10.5142     0.0000    10.0000 </r>
       <r>   -10.4149     0.0000    10.0000 </r>
       <r>   -10.3157     0.0000    10.0000 </r>
       <r>   -10.2164     0.0000    10.0000 </r>
       <r>   -10.1172     0.0000    10.0000 </r>
       <r>   -10.0179     0.0000    10.0000 </r>
       <r>    -9.9187     0.0000    10.0000 </r>
       <r>    -9.8194     0.0000    10.0000 </r>
       <r>    -9.7202     0.0000    10.0000 </r>
       <r>    -9.6209     0.0000    10.0000 </r>
       <r>    -9.5216     0.0000    10.0000 </r>
       <r>    -9.4224     0.0000    10.0000 </r>
       <r>    -9.3231     0.0000    10.0000 </r>
       <r>    -9.2239     0.0000    10.0000 </r>
       <r>    -9.1246     0.0000    10.0000 </r>
       <r>    -9.0254     0.0000    10.0000 </r>
       <r>    -8.9261     0.0000    10.0000 </r>
       <r>    -8.8269     0.0000    10.0000 </r>
       <r>    -8.7276     0.0000    10.0000 </r>
       <r>    -8.6284     0.0000    10.0000 </r>
       <r>    -8.5291     0.0000    10.0000 </r>
       <r>    -8.4298     0.0000    10.0000 </r>
       <r>    -8.3306     0.0000    10.0000 </r>
       <r>    -8.2313     0.0000    10.0000 </r>
       <r>    -8.1321     0.0000    10.0000 </r>
       <r>    -8.0328     0.0000    10.0000 </r>
       <r>    -7.9336     0.0000    10.0000 </r>
       <r>    -7.8343     0.0000    10.0000 </r>
       <r>    -7.7351     0.0000    10.0000 </r>
       <r>    -7.6358     0.0000    10.0000 </r>
       <r>    -7.5366     0.0000    10.0000 </r>
       <r>    -7.4373     0.0000    10.0000 </r>
       <r>    -7.3381     0.0000    10.0000 </r>
       <r>    -7.2388     0.0000    10.0000 </r>
       <r>    -7.1395     0.0000    10.0000 </r>
       <r>    -7.0403     0.0000    10.0000 </r>
       <r>    -6.9410     0.0000    10.0000 </r>
       <r>    -6.8418     0.0000    10.0000 </r>
       <r>    -6.7425     0.0000    10.0000 </r>
       <r>    -6.6433     0.0000    10.0000 </r>
       <r>    -6.5440     0.0000    10.0000 </r>
       <r>    -6.4448     0.0000    10.0000 </r>
       <r>    -6.3455     0.0000    10.0000 </r>
       <r>    -6.2463     0.0000    10.0000 </r>
       <r>    -6.1470     0.0000    10.0000 </r>
       <r>    -6.0477     0.0000    10.0000 </r>
       <r>    -5.9485     0.0000    10.0000 </r>
       <r>    -5.8492     0.0000    10.0000 </r>
       <r>    -5.7500     0.0000    10.0000 </r>
       <r>    -5.6507     0.0000    10.0000 </r>
       <r>    -5.5515     0.0000    10.0000 </r>
       <r>    -5.4522    -0.0000    10.0000 </r>
       <r>    -5.3530    -0.0000    10.0000 </r>
       <r>    -5.2537    -0.0000    10.0000 </r>
       <r>    -5.1545    -0.0000    10.0000 </r>
       <r>    -5.0552    -0.0000    10.0000 </r>
       <r>    -4.9559    -0.0000    10.0000 </r>
       <r>    -4.8567    -0.0004    10.0000 </r>
       <r>    -4.7574    -0.0243     9.9975 </r>
       <r>    -4.6582    -0.0803     9.9896 </r>
       <r>    -4.5589     1.0536    10.0942 </r>
       <r>    -4.4597     5.6933    10.6592 </r>
       <r>    -4.3604     9.8548    11.6374 </r>
       <r>    -4.2612     6.0955    12.2424 </r>
       <r>    -4.1619     6.8203    12.9193 </r>
       <r>    -4.0627     7.7413    13.6877 </r>
       <r>    -3.9634     4.2355    14.1081 </r>
       <r>    -3.8642     3.2878    14.4344 </r>
       <r>    -3.7649     7.8366    15.2122 </r>
       <r>    -3.6656     7.0913    15.9161 </r>
       <r>    -3.5664     1.0156    16.0169 </r>
       <r>    -3.4671     0.0661    16.0234 </r>
       <r>    -3.3679     1.7332    16.1955 </r>
       <r>    -3.2686     3.6532    16.5580 </r>
       <r>    -3.1694     5.3989    17.0939 </r>
       <r>    -3.0701     4.3447    17.5251 </r>
       <r>    -2.9709     2.6341    17.7866 </r>
       <r>    -2.8716     3.8595    18.1697 </r>
       <r>    -2.7724     5.5916    18.7247 </r>
       <r>    -2.6731     6.4774    19.3676 </r>
       <r>    -2.5738     2.8803    19.6534 </r>
       <r>    -2.4746     1.3185    19.7843 </r>
       <r>    -2.3753     4.1179    20.1930 </r>
       <r>    -2.2761     6.0207    20.7906 </r>
       <r>    -2.1768     7.4392    21.5290 </r>
       <r>    -2.0776     4.4525    21.9709 </r>
       <r>    -1.9783     0.8451    22.0548 </r>
       <r>    -1.8791     2.1214    22.2654 </r>
       <r>    -1.7798     4.7186    22.7337 </r>
       <r>    -1.6806     5.8855    23.3179 </r>
       <r>    -1.5813     4.7970    23.7940 </r>
       <r>    -1.4820     2.9982    24.0916 </r>
       <r>    -1.3828     2.0642    24.2964 </r>
       <r>    -1.2835     4.4827    24.7414 </r>
       <r>    -1.1843     5.2697    25.2644 </r>
       <r>    -1.0850     6.3478    25.8945 </r>
       <r>    -0.9858     1.2844    26.0219 </r>
       <r>    -0.8865     2.1584    26.2362 </r>
       <r>    -0.7873     2.5586    26.4901 </r>
       <r>    -0.6880     1.7562    26.6644 </r>
       <r>    -0.5888     4.8457    27.1454 </r>
       <r>    -0.4895     7.6544    27.9051 </r>
       <r>    -0.3902     6.4598    28.5463 </r>
       <r>    -0.2910     8.0800    29.3483 </r>
       <r>    -0.1917     6.2168    29.9653 </r>
       <r>    -0.0925     5.4297    30.5042 </r>
       <r>     0.0068     4.4431    30.9452 </r>
       <r>     0.1060     5.6854    31.5095 </r>
       <r>     0.2053     8.5044    32.3536 </r>
       <r>     0.3045     6.2797    32.9769 </r>
       <r>     0.4038     5.7116    33.5438 </r>
       <r>     0.5030     7.3943    34.2777 </r>
       <r>     0.6023     5.2773    34.8015 </r>
       <r>     0.7015     5.8384    35.3810 </r>
       <r>     0.8008     4.8381    35.8612 </r>
       <r>     0.9001     9.6994    36.8239 </r>
       <r>     0.9993     6.5516    37.4742 </r>
       <r>     1.0986     1.2476    37.5980 </r>
       <r>     1.1978     3.6628    37.9616 </r>
       <r>     1.2971     7.2184    38.6780 </r>
       <r>     1.3963    11.3236    39.8020 </r>
       <r>     1.4956     6.3142    40.4287 </r>
       <r>     1.5948     6.1844    41.0425 </r>
       <r>     1.6941     7.6217    41.7990 </r>
       <r>     1.7933     6.7651    42.4705 </r>
       <r>     1.8926     9.2113    43.3847 </r>
       <r>     1.9919     6.2525    44.0053 </r>
       <r>     2.0911     7.8438    44.7838 </r>
       <r>     2.1904     7.4720    45.5255 </r>
       <r>     2.2896     9.5763    46.4760 </r>
       <r>     2.3889     9.1952    47.3886 </r>
       <r>     2.4881     5.7027    47.9546 </r>
       <r>     2.5874     8.4478    48.7931 </r>
       <r>     2.6866     9.6517    49.7511 </r>
       <r>     2.7859     6.3572    50.3821 </r>
       <r>     2.8851     3.8291    50.7621 </r>
       <r>     2.9844     6.4450    51.4018 </r>
       <r>     3.0837    10.1206    52.4063 </r>
       <r>     3.1829    10.1088    53.4097 </r>
       <r>     3.2822     7.2294    54.1272 </r>
       <r>     3.3814     4.9316    54.6167 </r>
       <r>     3.4807     6.1749    55.2296 </r>
       <r>     3.5799     5.9757    55.8227 </r>
       <r>     3.6792     1.8597    56.0073 </r>
       <r>     3.7784     1.4334    56.1496 </r>
       <r>     3.8777     7.6103    56.9049 </r>
       <r>     3.9769     9.9002    57.8876 </r>
       <r>     4.0762     6.8853    58.5710 </r>
       <r>     4.1754     7.2646    59.2920 </r>
       <r>     4.2747     5.8735    59.8750 </r>
       <r>     4.3740     3.7194    60.2441 </r>
       <r>     4.4732     6.7045    60.9096 </r>
       <r>     4.5725     5.0612    61.4119 </r>
       <r>     4.6717     4.5811    61.8666 </r>
       <r>     4.7710     5.9806    62.4602 </r>
       <r>     4.8702     4.3920    62.8961 </r>
       <r>     4.9695     5.2136    63.4136 </r>
       <r>     5.0687     5.3432    63.9439 </r>
       <r>     5.1680     4.9966    64.4399 </r>
       <r>     5.2672     6.7327    65.1081 </r>
       <r>     5.3665     8.6048    65.9622 </r>
       <r>     5.4658     5.2414    66.4824 </r>
       <r>     5.5650     4.2773    66.9070 </r>
       <r>     5.6643     6.8008    67.5820 </r>
       <r>     5.7635     6.0774    68.1852 </r>
       <r>     5.8628     6.7614    68.8563 </r>
       <r>     5.9620     7.1807    69.5690 </r>
       <r>     6.0613     3.6140    69.9277 </r>
       <r>     6.1605     1.9274    70.1190 </r>
       <r>     6.2598     0.2846    70.1472 </r>
       <r>     6.3590     1.4818    70.2943 </r>
       <r>     6.4583     2.4088    70.5334 </r>
       <r>     6.5576     0.6196    70.5949 </r>
       <r>     6.6568     0.1445    70.6093 </r>
       <r>     6.7561     1.2935    70.7376 </r>
       <r>     6.8553     2.8002    71.0156 </r>
       <r>     6.9546     2.4472    71.2585 </r>
       <r>     7.0538     2.4787    71.5045 </r>
       <r>     7.1531     2.9387    71.7962 </r>
       <r>     7.2523     1.9138    71.9861 </r>
       <r>     7.3516     0.1567    72.0017 </r>
       <r>     7.4508    -0.2173    71.9801 </r>
       <r>     7.5501     2.5118    72.2294 </r>
       <r>     7.6494     5.8057    72.8057 </r>
       <r>     7.7486     4.4248    73.2448 </r>
       <r>     7.8479     2.6106    73.5040 </r>
       <r>     7.9471     4.5175    73.9523 </r>
       <r>     8.0464     4.8228    74.4310 </r>
       <r>     8.1456     2.5431    74.6834 </r>
       <r>     8.2449     6.3550    75.3142 </r>
       <r>     8.3441     5.6526    75.8752 </r>
       <r>     8.4434     4.2302    76.2951 </r>
       <r>     8.5426     4.4731    76.7391 </r>
       <r>     8.6419     4.3375    77.1696 </r>
       <r>     8.7411     8.1919    77.9827 </r>
       <r>     8.8404     9.7091    78.9464 </r>
       <r>     8.9397     9.7028    79.9094 </r>
       <r>     9.0389     6.4262    80.5472 </r>
       <r>     9.1382     5.9349    81.1363 </r>
       <r>     9.2374     5.5375    81.6859 </r>
       <r>     9.3367     7.9127    82.4713 </r>
       <r>     9.4359     8.7269    83.3375 </r>
       <r>     9.5352     5.0197    83.8357 </r>
       <r>     9.6344     6.4408    84.4750 </r>
       <r>     9.7337     8.2618    85.2950 </r>
       <r>     9.8329     6.2503    85.9154 </r>
       <r>     9.9322     5.0659    86.4182 </r>
       <r>    10.0315     7.9380    87.2060 </r>
       <r>    10.1307     5.8145    87.7832 </r>
       <r>    10.2300     1.5714    87.9391 </r>
       <r>    10.3292     5.2291    88.4581 </r>
       <r>    10.4285     9.2020    89.3715 </r>
       <r>    10.5277     4.7659    89.8445 </r>
       <r>    10.6270     3.8145    90.2231 </r>
       <r>    10.7262     4.8139    90.7009 </r>
       <r>    10.8255     5.0208    91.1993 </r>
       <r>    10.9247     5.9132    91.7862 </r>
       <r>    11.0240     7.5925    92.5398 </r>
       <r>    11.1233     7.2454    93.2589 </r>
       <r>    11.2225     4.5498    93.7105 </r>
       <r>    11.3218     4.2968    94.1370 </r>
       <r>    11.4210     7.8134    94.9125 </r>
       <r>    11.5203     6.3895    95.5467 </r>
       <r>    11.6195     2.5260    95.7974 </r>
       <r>    11.7188     1.9307    95.9890 </r>
       <r>    11.8180     0.1694    96.0058 </r>
       <r>    11.9173    -0.0570    96.0002 </r>
       <r>    12.0165    -0.0016    96.0000 </r>
       <r>    12.1158    -0.0000    96.0000 </r>
       <r>    12.2150    -0.0000    96.0000 </r>
       <r>    12.3143    -0.0000    96.0000 </r>
       <r>    12.4136     0.0000    96.0000 </r>
       <r>    12.5128     0.0000    96.0000 </r>
       <r>    12.6121     0.0000    96.0000 </r>
       <r>    12.7113     0.0000    96.0000 </r>
       <r>    12.8106     0.0000    96.0000 </r>
       <r>    12.9098     0.0000    96.0000 </r>
       <r>    13.0091     0.0000    96.0000 </r>
      </set>
     </set>
    </array>
   </total>
  </dos>
 </calculation>
 <structure name="finalpos" >
  <crystal>
   <varray name="basis" >
    <v>       6.12463900       0.07338700       0.11643400 </v>
    <v>       0.10284100       6.12337600       0.21606000 </v>
    <v>       0.22619200       0.19802000       5.89217100 </v>
   </varray>
   <i name="volume">    220.51502595 </i>
   <varray name="rec_basis" >
    <v>       0.16342285      -0.00252629      -0.00618867 </v>
    <v>      -0.00185635       0.16353119      -0.00542458 </v>
    <v>      -0.00316130      -0.00594660       0.17003794 </v>
   </varray>
  </crystal>
  <varray name="positions" >
   <v>       0.24546400       0.23212500       0.23084700 </v>
   <v>       0.80047100       0.80006400       0.19867800 </v>
   <v>       0.81033100       0.17152300       0.80891400 </v>
   <v>       0.18090500       0.81913800       0.82178900 </v>
   <v>       0.34804700       0.47449400       0.92751700 </v>
   <v>       0.72514900       0.50278200       0.98477200 </v>
   <v>       0.45032700       0.92236300       0.34010900 </v>
   <v>       0.93168800       0.32030900       0.44130700 </v>
   <v>       0.00404300       0.69071400       0.51642700 </v>
   <v>       0.46317000       0.06007600       0.71053100 </v>
   <v>       0.96063700       0.96847700       0.98190400 </v>
   <v>       0.72040100       0.33498400       0.27410200 </v>
   <v>       0.27475100       0.71797200       0.34199700 </v>
   <v>       0.33859400       0.31511100       0.70081800 </v>
   <v>       0.76636700       0.65686500       0.71529900 </v>
  </varray>
 </structure>
</modeling>
